gvapi/__init__.py
gvapi/cli.py
gvapi/errors.py
gvapi/hero.py
gvapi/pet.py
gvapi/util.py
gvapi-0.8.dist-info/LICENSE
gvapi-0.8.dist-info/METADATA
gvapi-0.8.dist-info/WHEEL
gvapi-0.8.dist-info/entry_points.txt
gvapi-0.8.dist-info/top_level.txt
gvapi-0.8.dist-info/RECORD
