Metadata-Version: 2.1
Name: gvapi
Version: 0.8
Summary: Неофициальная обертка для API godville.net.
Home-page: https://github.com/TitaniumHocker/gvapi
Author: TitaniumHocker (Ivan Fedorov)
Author-email: inbox@titaniumhocker.ru
License: MIT
Project-URL: Documentation, https://gvapi.rtfd.io/
Project-URL: Issue tracker, https://github.com/TitaniumHocker/gvapi/issues
Platform: UNKNOWN
Classifier: Development Status :: 4 - Beta
Classifier: License :: OSI Approved :: MIT License
Classifier: Programming Language :: Python
Classifier: Programming Language :: Python :: 3 :: Only
Classifier: Programming Language :: Python :: 3.5
Classifier: Programming Language :: Python :: 3.6
Classifier: Programming Language :: Python :: 3.7
Classifier: Programming Language :: Python :: 3.8
Classifier: Intended Audience :: Developers
Classifier: Natural Language :: Russian
Classifier: Operating System :: OS Independent
Classifier: Environment :: Console
Classifier: Topic :: Internet
Classifier: Topic :: Software Development :: Libraries
Classifier: Topic :: Software Development :: Libraries :: Python Modules
Classifier: Topic :: Utilities 
Requires-Dist: requests
Requires-Dist: click
